iptvname/__init__.py
iptvname/get_iptv.py
iptvname/iptv.py
iptvname-0.0.2.dist-info/METADATA
iptvname-0.0.2.dist-info/WHEEL
iptvname-0.0.2.dist-info/top_level.txt
iptvname-0.0.2.dist-info/RECORD
